{"inkVersion":21,"root":[[["done",{"#n":"g-0"}],null],"done",{"director_morgan":["ev",{"VAR?":"mission_started"},false,"==","/ev",[{"->":".^.b","c":true},{"b":["\n","^Director Morgan is reviewing tactical displays, coordinating the response across all four crisis zones.","\n","^\"Agent 0x00. Ready for your briefing?\" ","#","^speaker:Director Morgan","/#","\n","ev","str","^I'm ready","/str","/ev",{"*":".^.c-0","flg":4},"ev","str","^Tell me about the other teams","/str","/ev",{"*":".^.c-1","flg":4},"ev","str","^Who is The Architect?","/str","/ev",{"*":".^.c-2","flg":4},{"->":".^.^.^.6"},{"c-0":["\n","^\"Good. Let's go over your assignment.\"","\n","ev",true,"/ev",{"VAR=":"mission_started","re":true},{"->":"mission_status"},null],"c-1":["^ ",{"->":"other_teams_status"},"\n",null],"c-2":["^ ",{"->":"architect_discussion"},"\n",null]}]}],"nop","\n","ev",{"VAR?":"mission_started"},true,"==","/ev",[{"->":".^.b","c":true},{"b":["\n","^Director Morgan looks up from her terminal as you approach.","\n","^\"Agent 0x00. Status update?\" ","#","^speaker:Director Morgan","/#","\n","ev","str","^Request situation update","/str","/ev",{"*":".^.c-0","flg":4},"ev","str","^Ask about other SAFETYNET teams","/str","/ev",{"*":".^.c-1","flg":4},"ev","str","^Ask about The Architect","/str","/ev",{"*":".^.c-2","flg":4},"ev","str","^Ask about intelligence findings","/str",{"VAR?":"flag1_submitted"},{"VAR?":"flag2_submitted"},"&&","/ev",{"*":".^.c-3","flg":5},"ev","str","^Request tactical guidance","/str",{"VAR?":"crisis_neutralized"},"!","/ev",{"*":".^.c-4","flg":5},"ev","str","^That's all for now","/str","/ev",{"*":".^.c-5","flg":4},{"->":".^.^.^.14"},{"c-0":["^ ",{"->":"mission_status"},"\n",null],"c-1":["^ ",{"->":"other_teams_status"},"\n",null],"c-2":["^ ",{"->":"architect_discussion"},"\n",null],"c-3":["^ ",{"->":"intelligence_discussion"},"\n",null],"c-4":["^ ",{"->":"tactical_guidance"},"\n",null],"c-5":["^ ","end","\n",null]}]}],"nop","\n",null],"mission_status":[["^She brings up your mission status display.","\n","ev",{"VAR?":"flag1_submitted"},"!",{"VAR?":"flag2_submitted"},"!","&&",{"VAR?":"flag3_submitted"},"!","&&",{"VAR?":"flag4_submitted"},"!","&&","/ev",[{"->":".^.b","c":true},{"b":["\n","^\"You haven't submitted any flags yet. Access the VM in the Server Room and begin exploitation. We need that intelligence to neutralize the attack.\" ","#","^speaker:Director Morgan","/#","\n",{"->":".^.^.^.16"},null]}],"nop","\n","ev",{"VAR?":"flag1_submitted"},{"VAR?":"flag2_submitted"},"!","&&","/ev",[{"->":".^.b","c":true},{"b":["\n","^\"One flag submitted. Good progress, but we need all four to extract the shutdown codes. Keep pushing.\" ","#","^speaker:Director Morgan","/#","\n",{"->":".^.^.^.25"},null]}],"nop","\n","ev",{"VAR?":"flag1_submitted"},{"VAR?":"flag2_submitted"},"&&",{"VAR?":"flag3_submitted"},"!","&&","/ev",[{"->":".^.b","c":true},{"b":["\n","^\"Two flags down. You're halfway there. Clock is ticking, Agent.\" ","#","^speaker:Director Morgan","/#","\n",{"->":".^.^.^.36"},null]}],"nop","\n","ev",{"VAR?":"flag1_submitted"},{"VAR?":"flag2_submitted"},"&&",{"VAR?":"flag3_submitted"},"&&",{"VAR?":"flag4_submitted"},"!","&&","/ev",[{"->":".^.b","c":true},{"b":["\n","^\"Three flags submitted. One more and you'll have everything you need to stop this. Final push.\" ","#","^speaker:Director Morgan","/#","\n",{"->":".^.^.^.49"},null]}],"nop","\n","ev",{"VAR?":"all_flags_submitted"},{"VAR?":"crisis_neutralized"},"!","&&","/ev",[{"->":".^.b","c":true},{"b":["\n","^\"All flags submitted. Excellent work. Now use that intelligence to neutralize the threat. Get to the Crisis Terminal and stop this attack.\" ","#","^speaker:Director Morgan","/#","\n",{"->":".^.^.^.58"},null]}],"nop","\n","ev",{"VAR?":"crisis_neutralized"},"/ev",[{"->":".^.b","c":true},{"b":["\n","^\"Crisis neutralized. Outstanding work, Agent. But the mission isn't over - search for intelligence about ENTROPY's broader operations.\" ","#","^speaker:Director Morgan","/#","\n",{"->":".^.^.^.64"},null]}],"nop","\n","ev","str","^Continue conversation","/str","/ev",{"*":".^.c-0","flg":4},"ev","str","^End conversation","/str","/ev",{"*":".^.c-1","flg":4},{"c-0":["^ ",{"->":"director_morgan"},"\n",null],"c-1":["^ ","end","\n",null]}],null],"other_teams_status":[["ev",true,"/ev",{"VAR=":"asked_about_other_teams","re":true},"^She switches to a tactical overview showing all four operations.","\n","^\"Here's what's happening at the other targets:\" ","#","^speaker:Director Morgan","/#","\n",[["ev",{"^->":"other_teams_status.0.11.0.$r1"},{"temp=":"$r"},"str",{"->":".^.s"},[{"#n":"$r1"}],"/str","/ev",{"*":".^.^.c-0","flg":18},{"s":["^TEAM ALPHA** - Current Status: ENGAGED",{"->":"$r","var":true},null]}],["ev",{"^->":"other_teams_status.0.11.1.$r1"},{"temp=":"$r"},"str",{"->":".^.s"},[{"#n":"$r1"}],"/str","/ev",{"*":".^.^.c-1","flg":18},{"s":["^TEAM BRAVO** - Current Status: ENGAGED",{"->":"$r","var":true},null]}],["ev",{"^->":"other_teams_status.0.11.2.$r1"},{"temp=":"$r"},"str",{"->":".^.s"},[{"#n":"$r1"}],"/str","/ev",{"*":".^.^.c-2","flg":18},{"s":["^TEAM CHARLIE** - Current Status: ENGAGED",{"->":"$r","var":true},null]}],{"c-0":["ev",{"^->":"other_teams_status.0.11.c-0.$r2"},"/ev",{"temp=":"$r"},{"->":".^.^.0.s"},[{"#n":"$r2"}],"\n","ev",{"VAR?":"crisis_choice"},"str","^infrastructure","/str","==","/ev",[{"->":".^.b","c":true},{"b":["^ Supply Chain operation - Proceeding as expected",{"->":".^.^.^.15"},null]}],"nop","\n","ev",{"VAR?":"crisis_choice"},"str","^data","/str","==","/ev",[{"->":".^.b","c":true},{"b":["^ Infrastructure operation - Facing heavy resistance, casualties expected",{"->":".^.^.^.25"},null]}],"nop","\n","ev",{"VAR?":"crisis_choice"},"str","^supply_chain","/str","==","/ev",[{"->":".^.b","c":true},{"b":["^ Data Apocalypse operation - Both attacks prevented, clean success",{"->":".^.^.^.35"},null]}],"nop","\n","ev",{"VAR?":"crisis_choice"},"str","^corporate","/str","==","/ev",[{"->":".^.b","c":true},{"b":["^ Infrastructure operation - Attack neutralized successfully",{"->":".^.^.^.45"},null]}],"nop","\n",{"#f":5}],"c-1":["ev",{"^->":"other_teams_status.0.11.c-1.$r2"},"/ev",{"temp=":"$r"},{"->":".^.^.1.s"},[{"#n":"$r2"}],"\n","ev",{"VAR?":"crisis_choice"},"str","^infrastructure","/str","==","/ev",[{"->":".^.b","c":true},{"b":["^ Data Apocalypse - Partial success, data breach stopped but disinformation deployed",{"->":".^.^.^.15"},null]}],"nop","\n","ev",{"VAR?":"crisis_choice"},"str","^data","/str","==","/ev",[{"->":".^.b","c":true},{"b":["^ Corporate Warfare operation - All zero-days neutralized",{"->":".^.^.^.25"},null]}],"nop","\n","ev",{"VAR?":"crisis_choice"},"str","^supply_chain","/str","==","/ev",[{"->":".^.b","c":true},{"b":["^ Infrastructure operation - Partial success, some casualties",{"->":".^.^.^.35"},null]}],"nop","\n","ev",{"VAR?":"crisis_choice"},"str","^corporate","/str","==","/ev",[{"->":".^.b","c":true},{"b":["^ Data Apocalypse operation - CRITICAL FAILURE, both attacks succeeded",{"->":".^.^.^.45"},null]}],"nop","\n",{"#f":5}],"c-2":["ev",{"^->":"other_teams_status.0.11.c-2.$r2"},"/ev",{"temp=":"$r"},{"->":".^.^.2.s"},[{"#n":"$r2"}],"\n","ev",{"VAR?":"crisis_choice"},"str","^infrastructure","/str","==","/ev",[{"->":".^.b","c":true},{"b":["^ Corporate Warfare - Zero-days deployed, economic damage occurring",{"->":".^.^.^.15"},null]}],"nop","\n","ev",{"VAR?":"crisis_choice"},"str","^data","/str","==","/ev",[{"->":".^.b","c":true},{"b":["^ Supply Chain operation - Partial success, some backdoors prevented",{"->":".^.^.^.25"},null]}],"nop","\n","ev",{"VAR?":"crisis_choice"},"str","^supply_chain","/str","==","/ev",[{"->":".^.b","c":true},{"b":["^ Corporate Warfare - Zero-days deployed, economic damage confirmed",{"->":".^.^.^.35"},null]}],"nop","\n","ev",{"VAR?":"crisis_choice"},"str","^corporate","/str","==","/ev",[{"->":".^.b","c":true},{"b":["^ Supply Chain operation - Partial success, most backdoors prevented",{"->":".^.^.^.45"},null]}],"nop","\n","^She looks at you with professional calm.","\n","^\"The outcomes are unfolding exactly as the models predicted. Your choice determined which crisis gets the best operator - you. The others... they're doing their best.\"","\n","^A pause.","\n","^\"Focus on your mission. You can't help them now. Win YOUR battle.\"","\n",{"#f":5}]}],"ev","str","^Understood","/str","/ev",{"*":".^.c-0","flg":4},"ev","str","^What about casualties?","/str","/ev",{"*":".^.c-1","flg":4},{"c-0":["^ ",{"->":"director_morgan"},"\n",null],"c-1":["^ ",{"->":"casualties_discussion"},"\n",null]}],null],"casualties_discussion":[["^Her expression is grim.","\n","^\"We're tracking casualty estimates in real-time based on team performance.\" ","#","^speaker:Director Morgan","/#","\n","ev",{"VAR?":"crisis_choice"},"str","^infrastructure","/str","==","/ev",[{"->":".^.b","c":true},{"b":["\n","^\"Team Bravo stopped the voter data breach, but Social Fabric's disinformation campaign launched. We're seeing civil unrest beginning - estimated 20-40 deaths if it escalates.\"","\n","^\"Team Charlie failed to stop the corporate zero-day attacks. Healthcare ransomware is active at 840 hospitals. Surgeries cancelled. We're projecting 80-140 deaths from delayed medical care.\"","\n",{"->":".^.^.^.15"},null]}],"nop","\n","ev",{"VAR?":"crisis_choice"},"str","^data","/str","==","/ev",[{"->":".^.b","c":true},{"b":["\n","^\"Team Alpha couldn't stop the infrastructure attack. Pacific Northwest is going dark. We're estimating 240-385 civilian deaths over 72 hours. Hospital generators, traffic accidents, hypothermia exposure.\"","\n",{"->":".^.^.^.25"},null]}],"nop","\n","ev",{"VAR?":"crisis_choice"},"str","^supply_chain","/str","==","/ev",[{"->":".^.b","c":true},{"b":["\n","^\"Team Bravo prevented infrastructure casualties - full success there. But Team Charlie failed on corporate. Healthcare ransomware active, economic damage mounting.\"","\n",{"->":".^.^.^.35"},null]}],"nop","\n","ev",{"VAR?":"crisis_choice"},"str","^corporate","/str","==","/ev",[{"->":".^.b","c":true},{"b":["\n","^\"Team Bravo failed. Both data attacks succeeded - voter breach AND disinformation. We're seeing civil unrest. Estimated casualties 20-40 and climbing.\"","\n",{"->":".^.^.^.45"},null]}],"nop","\n","^She meets your eyes.","\n","^\"These numbers are real people, Agent. But you made the best choice you could. Now win yours so the total damage is minimized.\"","\n","ev","str","^I understand","/str","/ev",{"*":".^.c-0","flg":4},{"c-0":["^ ",{"->":"director_morgan"},"\n",null]}],null],"architect_discussion":[["ev",true,"/ev",{"VAR=":"asked_about_architect","re":true},"^Director Morgan pulls up an intelligence file marked \"ENTROPY - THE ARCHITECT - CLASSIFIED.\"","\n","^\"Everything we know about The Architect is speculation and pattern analysis.\" ","#","^speaker:Director Morgan","/#","\n","^\"**What we know for certain:**","\n",["ev",{"^->":"architect_discussion.0.13.$r1"},{"temp=":"$r"},"str",{"->":".^.s"},[{"#n":"$r1"}],"/str","/ev",{"*":".^.^.c-0","flg":18},{"s":["^Coordinates all ENTROPY cells with precision",{"->":"$r","var":true},null]}],["ev",{"^->":"architect_discussion.0.14.$r1"},{"temp=":"$r"},"str",{"->":".^.s"},[{"#n":"$r1"}],"/str","/ev",{"*":".^.^.c-1","flg":18},{"s":["^Deep knowledge of SAFETYNET protocols and response capabilities",{"->":"$r","var":true},null]}],["ev",{"^->":"architect_discussion.0.15.$r1"},{"temp=":"$r"},"str",{"->":".^.s"},[{"#n":"$r1"}],"/str","/ev",{"*":".^.^.c-2","flg":18},{"s":["^Strategic thinker - designs operations to force impossible choices",{"->":"$r","var":true},null]}],["ev",{"^->":"architect_discussion.0.16.$r1"},{"temp=":"$r"},"str",{"->":".^.s"},[{"#n":"$r1"}],"/str","/ev",{"*":".^.^.c-3","flg":18},{"s":["^Communicates via encrypted channels, taunts operatives during missions",{"->":"$r","var":true},null]}],["ev",{"^->":"architect_discussion.0.17.$r1"},{"temp=":"$r"},"str",{"->":".^.s"},[{"#n":"$r1"}],"/str","/ev",{"*":".^.^.c-4","flg":18},{"s":["^Philosophy: 'Accelerating entropy' - believes in forcing societal collapse",{"->":"$r","var":true},null]}],["ev",{"^->":"architect_discussion.0.18.$r1"},{"temp=":"$r"},"str",{"->":".^.s"},[{"#n":"$r1"}],"/str","/ev",{"*":".^.^.c-5","flg":18},{"s":["^Former intelligence community (NSA, CIA, or military intelligence)",{"->":"$r","var":true},null]}],["ev",{"^->":"architect_discussion.0.19.$r1"},{"temp=":"$r"},"str",{"->":".^.s"},[{"#n":"$r1"}],"/str","/ev",{"*":".^.^.c-6","flg":18},{"s":["^Access to classified information about US infrastructure vulnerabilities",{"->":"$r","var":true},null]}],["ev",{"^->":"architect_discussion.0.20.$r1"},{"temp=":"$r"},"str",{"->":".^.s"},[{"#n":"$r1"}],"/str","/ev",{"*":".^.^.c-7","flg":18},{"s":["^Possibly knows SAFETYNET personnel (references to specific operators)",{"->":"$r","var":true},null]}],["ev",{"^->":"architect_discussion.0.21.$r1"},{"temp=":"$r"},"str",{"->":".^.s"},[{"#n":"$r1"}],"/str","/ev",{"*":".^.^.c-8","flg":18},{"s":["^The alias 'The Architect' suggests systematic planning, building toward something",{"->":"$r","var":true},null]}],["ev",{"^->":"architect_discussion.0.22.$r1"},{"temp=":"$r"},"str",{"->":".^.s"},[{"#n":"$r1"}],"/str","/ev",{"*":".^.^.c-9","flg":18},{"s":["^True identity",{"->":"$r","var":true},null]}],["ev",{"^->":"architect_discussion.0.23.$r1"},{"temp=":"$r"},"str",{"->":".^.s"},[{"#n":"$r1"}],"/str","/ev",{"*":".^.^.c-10","flg":18},{"s":["^Ultimate goal (beyond 'accelerated entropy')",{"->":"$r","var":true},null]}],["ev",{"^->":"architect_discussion.0.24.$r1"},{"temp=":"$r"},"str",{"->":".^.s"},[{"#n":"$r1"}],"/str","/ev",{"*":".^.^.c-11","flg":18},{"s":["^How many cells they control",{"->":"$r","var":true},null]}],["ev",{"^->":"architect_discussion.0.25.$r1"},{"temp=":"$r"},"str",{"->":".^.s"},[{"#n":"$r1"}],"/str","/ev",{"*":".^.^.c-12","flg":18},{"s":["^Location of their command center (we call it 'Tomb Gamma' based on intercepts)\"",{"->":"$r","var":true},null]}],"ev","str","^How do they have SAFETYNET intelligence?","/str","/ev",{"*":".^.c-13","flg":4},"ev","str","^What's their ultimate goal?","/str","/ev",{"*":".^.c-14","flg":4},"ev","str","^Continue","/str","/ev",{"*":".^.c-15","flg":4},{"c-0":["ev",{"^->":"architect_discussion.0.c-0.$r2"},"/ev",{"temp=":"$r"},{"->":".^.^.13.s"},[{"#n":"$r2"}],"\n",{"#f":5}],"c-1":["ev",{"^->":"architect_discussion.0.c-1.$r2"},"/ev",{"temp=":"$r"},{"->":".^.^.14.s"},[{"#n":"$r2"}],"\n",{"#f":5}],"c-2":["ev",{"^->":"architect_discussion.0.c-2.$r2"},"/ev",{"temp=":"$r"},{"->":".^.^.15.s"},[{"#n":"$r2"}],"\n",{"#f":5}],"c-3":["ev",{"^->":"architect_discussion.0.c-3.$r2"},"/ev",{"temp=":"$r"},{"->":".^.^.16.s"},[{"#n":"$r2"}],"\n",{"#f":5}],"c-4":["ev",{"^->":"architect_discussion.0.c-4.$r2"},"/ev",{"temp=":"$r"},{"->":".^.^.17.s"},[{"#n":"$r2"}],"\n",[["ev",{"^->":"architect_discussion.0.c-4.7.0.$r1"},{"temp=":"$r"},"str",{"->":".^.s"},[{"#n":"$r1"}],"/str","/ev",{"*":".^.^.c-0","flg":18},{"s":["^What we suspect:**",{"->":"$r","var":true},null]}],{"c-0":["ev",{"^->":"architect_discussion.0.c-4.7.c-0.$r2"},"/ev",{"temp=":"$r"},{"->":".^.^.0.s"},[{"#n":"$r2"}],"\n",{"#f":5}]}],{"#f":5}],"c-5":["ev",{"^->":"architect_discussion.0.c-5.$r2"},"/ev",{"temp=":"$r"},{"->":".^.^.18.s"},[{"#n":"$r2"}],"\n",{"#f":5}],"c-6":["ev",{"^->":"architect_discussion.0.c-6.$r2"},"/ev",{"temp=":"$r"},{"->":".^.^.19.s"},[{"#n":"$r2"}],"\n",{"#f":5}],"c-7":["ev",{"^->":"architect_discussion.0.c-7.$r2"},"/ev",{"temp=":"$r"},{"->":".^.^.20.s"},[{"#n":"$r2"}],"\n",{"#f":5}],"c-8":["ev",{"^->":"architect_discussion.0.c-8.$r2"},"/ev",{"temp=":"$r"},{"->":".^.^.21.s"},[{"#n":"$r2"}],"\n",[["ev",{"^->":"architect_discussion.0.c-8.7.0.$r1"},{"temp=":"$r"},"str",{"->":".^.s"},[{"#n":"$r1"}],"/str","/ev",{"*":".^.^.c-0","flg":18},{"s":["^What we don't know:**",{"->":"$r","var":true},null]}],{"c-0":["ev",{"^->":"architect_discussion.0.c-8.7.c-0.$r2"},"/ev",{"temp=":"$r"},{"->":".^.^.0.s"},[{"#n":"$r2"}],"\n",{"#f":5}]}],{"#f":5}],"c-9":["ev",{"^->":"architect_discussion.0.c-9.$r2"},"/ev",{"temp=":"$r"},{"->":".^.^.22.s"},[{"#n":"$r2"}],"\n",{"#f":5}],"c-10":["ev",{"^->":"architect_discussion.0.c-10.$r2"},"/ev",{"temp=":"$r"},{"->":".^.^.23.s"},[{"#n":"$r2"}],"\n",{"#f":5}],"c-11":["ev",{"^->":"architect_discussion.0.c-11.$r2"},"/ev",{"temp=":"$r"},{"->":".^.^.24.s"},[{"#n":"$r2"}],"\n",{"#f":5}],"c-12":["ev",{"^->":"architect_discussion.0.c-12.$r2"},"/ev",{"temp=":"$r"},{"->":".^.^.25.s"},[{"#n":"$r2"}],"\n","^She closes the file.","\n","^\"They're the most sophisticated threat we've ever faced. And they're watching you right now.\"","\n",{"#f":5}],"c-13":["^ ",{"->":"mole_discussion"},"\n",null],"c-14":["^ ",{"->":"architect_goal_discussion"},"\n",null],"c-15":["^ ",{"->":"director_morgan"},"\n",null]}],null],"mole_discussion":[["ev",true,"/ev",{"VAR=":"asked_about_mole","re":true},"^Her voice drops.","\n","^\"We have a mole. Someone inside SAFETYNET feeding The Architect our operational details.\" ","#","^speaker:Director Morgan","/#","\n","^\"The timing of these four attacks - simultaneous, coordinated, designed to split our resources - that requires insider knowledge.\"","\n","^\"Your assignment to your specific target, the other teams' assignments, our response capabilities... The Architect knew it all before we deployed.\"","\n","^She looks around cautiously.","\n","^\"I don't know who. Could be anyone with access to operations. Could be... someone in this room.\"","\n","^\"If you find evidence during your mission - emails, communications, anything linking SAFETYNET personnel to ENTROPY - secure it immediately.\"","\n","ev","str","^I'll find them","/str","/ev",{"*":".^.c-0","flg":4},"ev","str","^How do we trust anyone?","/str","/ev",{"*":".^.c-1","flg":4},{"c-0":["^ ",{"->":"director_morgan"},"\n",null],"c-1":["^ ",{"->":"trust_discussion"},"\n",null]}],null],"trust_discussion":[["^\"We don't have the luxury of paranoia right now. We trust our training, our procedures, and each other - until evidence proves otherwise.\" ","#","^speaker:Director Morgan","/#","\n","^\"After tonight, we'll conduct a full internal investigation. But right now, focus on stopping the attack.\"","\n","^\"The mole can't help ENTROPY if ENTROPY fails.\"","\n","ev","str","^Understood","/str","/ev",{"*":".^.c-0","flg":4},{"c-0":["^ ",{"->":"director_morgan"},"\n",null]}],null],"architect_goal_discussion":[["^She brings up a strategic analysis display.","\n","^\"Our analysts believe The Architect is testing something. These coordinated attacks are a proof-of-concept.\" ","#","^speaker:Director Morgan","/#","\n","^\"**Hypothesis 1:** Training exercises for larger future operation","\n",[["ev",{"^->":"architect_goal_discussion.0.9.0.$r1"},{"temp=":"$r"},"str",{"->":".^.s"},[{"#n":"$r1"}],"/str","/ev",{"*":".^.^.c-0","flg":18},{"s":["^Hypothesis 2:** Demonstrating capability to recruit nation-state clients",{"->":"$r","var":true},null]}],["ev",{"^->":"architect_goal_discussion.0.9.1.$r1"},{"temp=":"$r"},"str",{"->":".^.s"},[{"#n":"$r1"}],"/str","/ev",{"*":".^.^.c-1","flg":18},{"s":["^Hypothesis 3:** Ideological - genuinely believes in accelerating societal collapse",{"->":"$r","var":true},null]}],["ev",{"^->":"architect_goal_discussion.0.9.2.$r1"},{"temp=":"$r"},"str",{"->":".^.s"},[{"#n":"$r1"}],"/str","/ev",{"*":".^.^.c-2","flg":18},{"s":["^Hypothesis 4:** Personal vendetta against someone in government/intelligence\"",{"->":"$r","var":true},null]}],{"c-0":["ev",{"^->":"architect_goal_discussion.0.9.c-0.$r2"},"/ev",{"temp=":"$r"},{"->":".^.^.0.s"},[{"#n":"$r2"}],"\n",{"#f":5}],"c-1":["ev",{"^->":"architect_goal_discussion.0.9.c-1.$r2"},"/ev",{"temp=":"$r"},{"->":".^.^.1.s"},[{"#n":"$r2"}],"\n",{"#f":5}],"c-2":["ev",{"^->":"architect_goal_discussion.0.9.c-2.$r2"},"/ev",{"temp=":"$r"},{"->":".^.^.2.s"},[{"#n":"$r2"}],"\n","^\"Honestly? We don't know. But tonight's attacks feel like... a rehearsal. Building toward something bigger.\"","\n","^She pauses.","\n","^\"That's why stopping them tonight is so critical. Not just for the immediate lives saved, but to disrupt whatever they're planning next.\"","\n",{"#f":5}]}],"ev","str","^We'll stop them","/str","/ev",{"*":".^.c-0","flg":4},{"c-0":["^ ",{"->":"director_morgan"},"\n",null]}],null],"tactical_guidance":[["^She reviews your mission profile.","\n","^\"Tactical guidance for your operation:\" ","#","^speaker:Director Morgan","/#","\n","ev",{"VAR?":"crisis_choice"},"str","^infrastructure","/str","==","/ev",[{"->":".^.b","c":true},{"b":["\n","^\"Priority: Reach the SCADA control room before the timer expires. Key Intel: Marcus Chen is a true believer. He won't surrender easily, but he's not suicidal. If you present evidence of civilian casualties, he might hesitate. VM Challenge: Focus on extracting shutdown codes from the NFS shares. You'll need root access to disable the attack scripts. Warning: Chen has backup operatives. Expect resistance, but avoid prolonged combat - you're on a clock.\"","\n",{"->":".^.^.^.16"},null]}],[{"->":".^.b"},{"b":["\n","ev",{"VAR?":"crisis_choice"},"str","^data","/str","==","/ev",[{"->":".^.b","c":true},{"b":["\n","^\"Priority: You're facing dual threats - data exfiltration AND disinformation deployment. Critical Choice: You may not be able to stop both. If forced to choose, prioritize based on your assessment of long-term vs. short-term damage. Key Intel: Rachel Morrow (Social Fabric) can be recruited. Show her evidence of ENTROPY's casualty projections - she thinks she's exposing corruption, not causing deaths. Warning: Specter (Ghost Protocol) will escape. Don't waste time chasing them - Ghost Protocol always has exit strategies.\"","\n",{"->":".^.^.^.10"},null]}],[{"->":".^.b"},{"b":["\n","ev",{"VAR?":"crisis_choice"},"str","^supply_chain","/str","==","/ev",[{"->":".^.b","c":true},{"b":["\n","^\"Priority: Disable backdoor injection before software updates deploy. Key Intel: Adrian Cross is philosophically opposed to supply chain vulnerabilities, not actually pro-murder. He's recruitable if shown casualty evidence. VM Challenge: Focus on quarantining already-modified updates AND preventing future injections. Strategic Value: If you recruit Adrian, he's valuable long-term - deep knowledge of supply chain attack methods.\"","\n",{"->":".^.^.^.10"},null]}],[{"->":".^.b"},{"b":["\n","^\"Priority: Deploy countermeasures to all 12 target corporations before zero-days deploy. Key Intel: Victoria Zhang (Digital Vanguard) is ideologically motivated, Marcus Chen (Zero Day Syndicate) is mercenary. Exploit that difference. VM Challenge: Extract countermeasure codes and deploy patches via the automated system. Warning: Marcus will escape. Victoria is recruitable - show her the casualty projections from the other operations.\"","\n",{"->":".^.^.^.10"},null]}],"nop","\n",{"->":".^.^.^.10"},null]}],"nop","\n",{"->":".^.^.^.16"},null]}],"nop","\n","^\"Good luck, Agent. You're our best operator for a reason.\"","\n","ev","str","^Thank you","/str","/ev",{"*":".^.c-0","flg":4},{"c-0":["^ ",{"->":"director_morgan"},"\n",null]}],null],"intelligence_discussion":[["^\"What have you found so far?\" ","#","^speaker:Director Morgan","/#","\n","ev","str","^Tell me what I should be looking for","/str","/ev",{"*":".^.c-0","flg":4},"ev","str","^I'm still gathering intelligence","/str","/ev",{"*":".^.c-1","flg":4},{"c-0":["^ ",{"->":"intel_targets"},"\n",null],"c-1":["^ ",{"->":"director_morgan"},"\n",null]}],null],"intel_targets":[["^She brings up an intelligence priority list.","\n","^\"**HIGH-PRIORITY INTELLIGENCE TARGETS:**","\n","^1. **Tomb Gamma Location** - The Architect's command center. We've intercepted references to coordinates, likely in communications on site.","\n","^2. **SAFETYNET Mole Evidence** - Any emails or messages between ENTROPY and someone with a SAFETYNET email address.","\n","^3. **ENTROPY Cell Structure** - How the different cells coordinate, who reports to The Architect.","\n","^4. **Future Operation Plans** - Any indication of what comes after tonight.","\n","^If you find any of this, it's critical for preventing future attacks.\"","\n","ev","str","^I'll search thoroughly","/str","/ev",{"*":".^.c-0","flg":4},{"c-0":["^ ",{"->":"director_morgan"},"\n","end",null]}],null],"global decl":["ev","str","^","/str",{"VAR=":"crisis_choice"},false,{"VAR=":"flag1_submitted"},false,{"VAR=":"flag2_submitted"},false,{"VAR=":"flag3_submitted"},false,{"VAR=":"flag4_submitted"},false,{"VAR=":"all_flags_submitted"},false,{"VAR=":"crisis_neutralized"},false,{"VAR=":"mission_started"},false,{"VAR=":"asked_about_other_teams"},false,{"VAR=":"asked_about_architect"},false,{"VAR=":"asked_about_mole"},"/ev","end",null]}],"listDefs":{}}